my_checker/__init__.py
my_checker/my_checker.py
my_checker-0.1.1.dist-info/DESCRIPTION.rst
my_checker-0.1.1.dist-info/METADATA
my_checker-0.1.1.dist-info/RECORD
my_checker-0.1.1.dist-info/WHEEL
my_checker-0.1.1.dist-info/metadata.json
my_checker-0.1.1.dist-info/top_level.txt
