Metadata-Version: 2.0
Name: my-checker
Version: 0.1.1
Summary: Quick math checker
Home-page: https://github.com/mareuter/my_checker
Author: Michael Reuter
Author-email: mareuternh@gmail.com
License: MIT
Keywords: my_checker
Platform: UNKNOWN
Classifier: Development Status :: 2 - Pre-Alpha
Classifier: Intended Audience :: Developers
Classifier: License :: OSI Approved :: MIT License
Classifier: Natural Language :: English
Classifier: Programming Language :: Python :: 2
Classifier: Programming Language :: Python :: 2.7
Classifier: Programming Language :: Python :: 3
Classifier: Programming Language :: Python :: 3.5
Classifier: Programming Language :: Python :: Implementation :: PyPy
